hopkins_statistic/__init__.py
hopkins_statistic/_statistic.py
hopkins_statistic/py.typed
hopkins_statistic-0.1.0.dist-info/licenses/LICENSE
hopkins_statistic-0.1.0.dist-info/WHEEL
hopkins_statistic-0.1.0.dist-info/METADATA
hopkins_statistic-0.1.0.dist-info/RECORD
