Metadata-Version: 2.4
Name: hopkins-statistic
Version: 0.1.0
Summary: Compute the Hopkins statistic to assess clustering tendency.
Keywords: clustering,clustering-tendency,data-mining,hopkins-statistic,machine-learning,statistics
Author: Johann Philipp Gorzny
License-Expression: MIT
License-File: LICENSE
Classifier: Development Status :: 4 - Beta
Classifier: Intended Audience :: Developers
Classifier: Intended Audience :: Science/Research
Classifier: Programming Language :: Python
Classifier: Programming Language :: Python :: 3
Classifier: Programming Language :: Python :: 3.11
Classifier: Programming Language :: Python :: 3.12
Classifier: Programming Language :: Python :: 3.13
Classifier: Programming Language :: Python :: 3.14
Classifier: Topic :: Scientific/Engineering :: Information Analysis
Classifier: Typing :: Typed
Requires-Dist: numpy>=2.0.0
Requires-Dist: scipy>=1.13.0
Requires-Python: >=3.11
Project-URL: Documentation, https://jo-phil.github.io/hopkins-statistic/
Project-URL: Repository, https://github.com/jo-phil/hopkins-statistic
